odoo/addons/sale_report_delivered_subtotal/README.rst
odoo/addons/sale_report_delivered_subtotal/__init__.py
odoo/addons/sale_report_delivered_subtotal/__manifest__.py
odoo/addons/sale_report_delivered_subtotal/i18n/es.po
odoo/addons/sale_report_delivered_subtotal/i18n/sale_report_delivered_subtotal.pot
odoo/addons/sale_report_delivered_subtotal/readme/CONTRIBUTORS.rst
odoo/addons/sale_report_delivered_subtotal/readme/DESCRIPTION.rst
odoo/addons/sale_report_delivered_subtotal/readme/USAGE.rst
odoo/addons/sale_report_delivered_subtotal/reports/__init__.py
odoo/addons/sale_report_delivered_subtotal/reports/sale_report.py
odoo/addons/sale_report_delivered_subtotal/static/description/icon.png
odoo/addons/sale_report_delivered_subtotal/static/description/index.html
odoo13_addon_sale_report_delivered_subtotal-13.0.1.1.0.dist-info/METADATA
odoo13_addon_sale_report_delivered_subtotal-13.0.1.1.0.dist-info/WHEEL
odoo13_addon_sale_report_delivered_subtotal-13.0.1.1.0.dist-info/top_level.txt
odoo13_addon_sale_report_delivered_subtotal-13.0.1.1.0.dist-info/RECORD
